axsemantics_cli/__init__.py
axsemantics_cli/analyze.py
axsemantics_cli/content_project.py
axsemantics_cli/convert_bmecat.py
axsemantics_cli/data_importer.py
axsemantics_cli/example.py
axsemantics_cli/importer.out
axsemantics_cli/main.py
axsemantics_cli/mapping_helpers.py
axsemantics_cli/setdefault.py
axsemantics_cli/training.py
axsemantics_cli/common/__init__.py
axsemantics_cli/common/cli_data.py
axsemantics_cli/common/formatter.py
axsemantics_cli/common/settings.py
axsemantics_cli/common/transfer.py
axsemantics_cli-0.1.4.dist-info/DESCRIPTION.rst
axsemantics_cli-0.1.4.dist-info/METADATA
axsemantics_cli-0.1.4.dist-info/RECORD
axsemantics_cli-0.1.4.dist-info/WHEEL
axsemantics_cli-0.1.4.dist-info/entry_points.txt
axsemantics_cli-0.1.4.dist-info/metadata.json
axsemantics_cli-0.1.4.dist-info/top_level.txt
