Metadata-Version: 2.0
Name: axsemantics-cli
Version: 0.1.4
Summary: AXSemantics API client Commandline Interface
Home-page: UNKNOWN
Author: Ramon Klass
Author-email: ramon.klass@ax-semantics.com
License: MIT
Platform: UNKNOWN
Classifier: License :: OSI Approved :: MIT License
Classifier: Programming Language :: Python :: 3
Classifier: Programming Language :: Python :: 3.3
Classifier: Programming Language :: Python :: 3.4
Classifier: Programming Language :: Python :: 3.5
Requires-Dist: appdirs
Requires-Dist: axsemantics
Requires-Dist: click
Requires-Dist: colorama
